{"chunks": [{"number": "4", "title": "Principle  of Optimality  - Dynamic Programming introduction - Abdul Bari", "start": 0.0, "end": 4.92, "text": " Hi the topic is dynamic programming in this video I'll give you introduction to dynamic"}, {"number": "4", "title": "Principle  of Optimality  - Dynamic Programming introduction - Abdul Bari", "start": 4.92, "end": 11.44, "text": " programming give you differences between dynamic programming and greedy method and also I will"}, {"number": "4", "title": "Principle  of Optimality  - Dynamic Programming introduction - Abdul Bari", "start": 11.44, "end": 18.28, "text": " show the difference between memoization and tabular method by taking an example in detail."}, {"number": "4", "title": "Principle  of Optimality  - Dynamic Programming introduction - Abdul Bari", "start": 18.28, "end": 22.48, "text": " Let us know the difference between greedy method and dynamic programming which is very"}, {"number": "4", "title": "Principle  of Optimality  - Dynamic Programming introduction - Abdul Bari", "start": 22.48, "end": 25.12, "text": " very important."}, {"number": "4", "title": "Principle  of Optimality  - Dynamic Programming introduction - Abdul Bari", "start": 25.12, "end": 30.720000000000002, "text": " Greedy method and dynamic programming both are used for solving optimization problems"}, {"number": "4", "title": "Principle  of Optimality  - Dynamic Programming introduction - Abdul Bari", "start": 30.720000000000002, "end": 35.08, "text": " both are different strategies but the purpose is same."}, {"number": "4", "title": "Principle  of Optimality  - Dynamic Programming introduction - Abdul Bari", "start": 35.08, "end": 40.92, "text": " Optimization problems are those which requires either minimum result or maximum result."}, {"number": "4", "title": "Principle  of Optimality  - Dynamic Programming introduction - Abdul Bari", "start": 40.92, "end": 47.8, "text": " The methods are different in greedy method we try to follow predefined procedure to get"}, {"number": "4", "title": "Principle  of Optimality  - Dynamic Programming introduction - Abdul Bari", "start": 47.8, "end": 49.44, "text": " the optimal result."}, {"number": "4", "title": "Principle  of Optimality  - Dynamic Programming introduction - Abdul Bari", "start": 49.44, "end": 56.839999999999996, "text": " The procedure is known to be optimal we follow the procedure to get best result like Kruskal's"}, {"number": "4", "title": "Principle  of Optimality  - Dynamic Programming introduction - Abdul Bari", "start": 56.839999999999996, "end": 62.699999999999996, "text": " method for finding minimum cost spanning tree always select a minimum cost edge and that"}, {"number": "4", "title": "Principle  of Optimality  - Dynamic Programming introduction - Abdul Bari", "start": 62.699999999999996, "end": 70.47999999999999, "text": " gives us best result or Dijkstra shortest path algorithm always select the shortest"}, {"number": "4", "title": "Principle  of Optimality  - Dynamic Programming introduction - Abdul Bari", "start": 70.47999999999999, "end": 76.96, "text": " path vertex and continue relaxing the vertices so you get the shortest path."}, {"number": "4", "title": "Principle  of Optimality  - Dynamic Programming introduction - Abdul Bari", "start": 76.96, "end": 82.47999999999999, "text": " So there is a predefined procedure but in dynamic programming we will try to find out"}, {"number": "4", "title": "Principle  of Optimality  - Dynamic Programming introduction - Abdul Bari", "start": 82.47999999999999, "end": 87.32, "text": " all possible solutions and then pick up the best solution the optimal solution."}, {"number": "4", "title": "Principle  of Optimality  - Dynamic Programming introduction - Abdul Bari", "start": 87.32, "end": 92.8, "text": " This approach is different and it is little time consuming compared to greedy method."}, {"number": "4", "title": "Principle  of Optimality  - Dynamic Programming introduction - Abdul Bari", "start": 92.8, "end": 98.32, "text": " For any problem there may be many solutions which are feasible so we will try out all"}, {"number": "4", "title": "Principle  of Optimality  - Dynamic Programming introduction - Abdul Bari", "start": 98.32, "end": 103.83999999999999, "text": " those solutions and then pick up the best one and mostly dynamic programming problems"}, {"number": "4", "title": "Principle  of Optimality  - Dynamic Programming introduction - Abdul Bari", "start": 103.84, "end": 111.48, "text": " are solved by using recursive formulas though we will not use recursion of programming but"}, {"number": "4", "title": "Principle  of Optimality  - Dynamic Programming introduction - Abdul Bari", "start": 111.48, "end": 117.24000000000001, "text": " the formulas are recursive if we want we can use recursion also but mostly they are solved"}, {"number": "4", "title": "Principle  of Optimality  - Dynamic Programming introduction - Abdul Bari", "start": 117.24000000000001, "end": 124.28, "text": " using iteration and dynamic programming follows principle of optimality."}, {"number": "4", "title": "Principle  of Optimality  - Dynamic Programming introduction - Abdul Bari", "start": 124.28, "end": 131.44, "text": " Principle of optimality says that a problem can be solved by taking sequence of decisions"}, {"number": "4", "title": "Principle  of Optimality  - Dynamic Programming introduction - Abdul Bari", "start": 131.44, "end": 132.84, "text": " to get the optimal solution."}, {"number": "4", "title": "Principle  of Optimality  - Dynamic Programming introduction - Abdul Bari", "start": 132.84, "end": 137.6, "text": " So now I can highlight one difference here in greedy method decision is taken one time"}, {"number": "4", "title": "Principle  of Optimality  - Dynamic Programming introduction - Abdul Bari", "start": 137.6, "end": 141.44, "text": " that we will do it like this and we follow that procedure."}, {"number": "4", "title": "Principle  of Optimality  - Dynamic Programming introduction - Abdul Bari", "start": 141.44, "end": 147.92, "text": " In dynamic programming every stage we take a decision so this point you can understand"}, {"number": "4", "title": "Principle  of Optimality  - Dynamic Programming introduction - Abdul Bari", "start": 147.92, "end": 152.22, "text": " only while solving the problem so while solving the problem I will show you perfectly how"}, {"number": "4", "title": "Principle  of Optimality  - Dynamic Programming introduction - Abdul Bari", "start": 152.22, "end": 156.28, "text": " dynamic programming is working there to solve a problem."}, {"number": "4", "title": "Principle  of Optimality  - Dynamic Programming introduction - Abdul Bari", "start": 156.28, "end": 162.64000000000001, "text": " Let us see how dynamic programming adopts tabulation method or memoization difference"}, {"number": "4", "title": "Principle  of Optimality  - Dynamic Programming introduction - Abdul Bari", "start": 162.64000000000001, "end": 164.92000000000002, "text": " between tabulation and memoization."}, {"number": "4", "title": "Principle  of Optimality  - Dynamic Programming introduction - Abdul Bari", "start": 164.92000000000002, "end": 170.96, "text": " I have an example function here this is the recursive definition of a Fibonacci term and"}, {"number": "4", "title": "Principle  of Optimality  - Dynamic Programming introduction - Abdul Bari", "start": 170.96, "end": 176.68, "text": " this is a function or an algorithm for finding Fibonacci term and it is a recursive function"}, {"number": "4", "title": "Principle  of Optimality  - Dynamic Programming introduction - Abdul Bari", "start": 176.68, "end": 180.36, "text": " the definition itself is recursive so the function is recursive."}, {"number": "4", "title": "Principle  of Optimality  - Dynamic Programming introduction - Abdul Bari", "start": 180.36, "end": 186.88000000000002, "text": " So what is Fibonacci series it starts from 0 and 1 1 every term is obtained by adding"}, {"number": "4", "title": "Principle  of Optimality  - Dynamic Programming introduction - Abdul Bari", "start": 186.88000000000002, "end": 194.60000000000002, "text": " previous two terms so 2 plus 1 that is 3 and 2 plus 3 that is 5 and 5 plus 3 that is 8"}, {"number": "4", "title": "Principle  of Optimality  - Dynamic Programming introduction - Abdul Bari", "start": 194.60000000000002, "end": 201.44000000000003, "text": " and this is 13 and so on so this is 0th term first term second third fourth fifth sixth"}, {"number": "4", "title": "Principle  of Optimality  - Dynamic Programming introduction - Abdul Bari", "start": 201.44000000000003, "end": 204.28000000000003, "text": " seventh and goes on."}, {"number": "4", "title": "Principle  of Optimality  - Dynamic Programming introduction - Abdul Bari", "start": 204.28, "end": 210.2, "text": " Suppose I want to know 10th term of Fibonacci series then call this function this function"}, {"number": "4", "title": "Principle  of Optimality  - Dynamic Programming introduction - Abdul Bari", "start": 210.2, "end": 213.4, "text": " will give us 10th term."}, {"number": "4", "title": "Principle  of Optimality  - Dynamic Programming introduction - Abdul Bari", "start": 213.4, "end": 218.04, "text": " Now I will show you how this function works if I want to find out any term because the"}, {"number": "4", "title": "Principle  of Optimality  - Dynamic Programming introduction - Abdul Bari", "start": 218.04, "end": 224.02, "text": " function is recursive so let us trace this function when I call this function for Fibonacci"}, {"number": "4", "title": "Principle  of Optimality  - Dynamic Programming introduction - Abdul Bari", "start": 224.02, "end": 231.76, "text": " of 5th term I want to find out if I trace this n is less than equal to 1 no it is not"}, {"number": "4", "title": "Principle  of Optimality  - Dynamic Programming introduction - Abdul Bari", "start": 231.76, "end": 238.07999999999998, "text": " less than equal to 1 if so then it will return n only otherwise it will call two functions"}, {"number": "4", "title": "Principle  of Optimality  - Dynamic Programming introduction - Abdul Bari", "start": 238.07999999999998, "end": 242.84, "text": " add their results and return the result so what are those two functions it is calling"}, {"number": "4", "title": "Principle  of Optimality  - Dynamic Programming introduction - Abdul Bari", "start": 242.84, "end": 252.39999999999998, "text": " it is calling itself for Fibonacci of 3 and Fibonacci of 4."}, {"number": "4", "title": "Principle  of Optimality  - Dynamic Programming introduction - Abdul Bari", "start": 252.39999999999998, "end": 257.71999999999997, "text": " So first of all it will call this one right then that one so if we see this again it will"}, {"number": "4", "title": "Principle  of Optimality  - Dynamic Programming introduction - Abdul Bari", "start": 257.72, "end": 262.68, "text": " enter inside and then it's not less than equal to 1 so it will call itself for 2 times"}, {"number": "4", "title": "Principle  of Optimality  - Dynamic Programming introduction - Abdul Bari", "start": 262.68, "end": 272.0, "text": " for 3 minus 2 that is Fib of 1 and then Fib of 2 then out of this it will pick up this"}, {"number": "4", "title": "Principle  of Optimality  - Dynamic Programming introduction - Abdul Bari", "start": 272.0, "end": 277.16, "text": " call first so Fib of 1 directly we get the answer 1 so this is 1 then it will come this"}, {"number": "4", "title": "Principle  of Optimality  - Dynamic Programming introduction - Abdul Bari", "start": 277.16, "end": 284.48, "text": " side so there are two calls here this is Fib of 0 and Fib of 1 for Fib of 0 and Fib of"}, {"number": "4", "title": "Principle  of Optimality  - Dynamic Programming introduction - Abdul Bari", "start": 284.48, "end": 290.48, "text": " 1 there is no recursive call direct result is return so here the functions terminates"}, {"number": "4", "title": "Principle  of Optimality  - Dynamic Programming introduction - Abdul Bari", "start": 290.48, "end": 295.40000000000003, "text": " then it will add these two terms and give the result it will add these two terms and"}, {"number": "4", "title": "Principle  of Optimality  - Dynamic Programming introduction - Abdul Bari", "start": 295.40000000000003, "end": 301.36, "text": " give the result then this side it has to continue so on this side again for Fibonacci of 4 it"}, {"number": "4", "title": "Principle  of Optimality  - Dynamic Programming introduction - Abdul Bari", "start": 301.36, "end": 308.08000000000004, "text": " will call itself for Fibonacci of 2 and this side for Fibonacci of 3 but first of all this"}, {"number": "4", "title": "Principle  of Optimality  - Dynamic Programming introduction - Abdul Bari", "start": 308.08, "end": 323.15999999999997, "text": " is done so this is Fib of 0 and Fib of 1 this side Fib of 1 and Fib of 2 again this"}, {"number": "4", "title": "Principle  of Optimality  - Dynamic Programming introduction - Abdul Bari", "start": 323.15999999999997, "end": 331.91999999999996, "text": " is Fib of 0 and Fib of 1 this will be the tracing tree of that particular function so"}, {"number": "4", "title": "Principle  of Optimality  - Dynamic Programming introduction - Abdul Bari", "start": 331.92, "end": 338.56, "text": " for finding Fib of 5 it is making total 15 calls now if I consider all the calls and"}, {"number": "4", "title": "Principle  of Optimality  - Dynamic Programming introduction - Abdul Bari", "start": 338.56, "end": 344.48, "text": " find out the time complexity of this one so from the function if I see this is n minus"}, {"number": "4", "title": "Principle  of Optimality  - Dynamic Programming introduction - Abdul Bari", "start": 344.48, "end": 349.76, "text": " 2 and that is n minus 1 if I assume roughly it is n minus 1 only then I can prepare a"}, {"number": "4", "title": "Principle  of Optimality  - Dynamic Programming introduction - Abdul Bari", "start": 349.76, "end": 356.04, "text": " recurrence relation for this one what it will be tn is equals to it is calling itself for"}, {"number": "4", "title": "Principle  of Optimality  - Dynamic Programming introduction - Abdul Bari", "start": 356.04, "end": 363.44, "text": " two time let us assume n minus 1 only so 2 tn minus 1 though this is n minus 2 but"}, {"number": "4", "title": "Principle  of Optimality  - Dynamic Programming introduction - Abdul Bari", "start": 363.44, "end": 369.76000000000005, "text": " if we take n minus 2 we cannot come to the conclusion so I am taking it as 1 right approximately"}, {"number": "4", "title": "Principle  of Optimality  - Dynamic Programming introduction - Abdul Bari", "start": 369.76000000000005, "end": 374.88, "text": " so this is 2 tn minus 1 and what it is doing every time just adding so this is the recurrence"}, {"number": "4", "title": "Principle  of Optimality  - Dynamic Programming introduction - Abdul Bari", "start": 374.88, "end": 381.72, "text": " relation and by master's theorem for decreasing function if you take this is big O of 2 power"}, {"number": "4", "title": "Principle  of Optimality  - Dynamic Programming introduction - Abdul Bari", "start": 381.72, "end": 388.36, "text": " n like this is not exact it is n minus 2 it is less I have taken n minus 1 only so"}, {"number": "4", "title": "Principle  of Optimality  - Dynamic Programming introduction - Abdul Bari", "start": 388.36, "end": 394.0, "text": " this upper bound for that function so the time taken by this function is big O of 2"}, {"number": "4", "title": "Principle  of Optimality  - Dynamic Programming introduction - Abdul Bari", "start": 394.0, "end": 399.40000000000003, "text": " power n right recurrence relation how to prepare there is a video available you can watch that"}, {"number": "4", "title": "Principle  of Optimality  - Dynamic Programming introduction - Abdul Bari", "start": 399.40000000000003, "end": 403.92, "text": " one so how to prepare a recurrence relation so this recurrence relation is big O of 2"}, {"number": "4", "title": "Principle  of Optimality  - Dynamic Programming introduction - Abdul Bari", "start": 403.92, "end": 409.24, "text": " power n means if I call this Fibonacci function it will take so much time 2 power n exponential"}, {"number": "4", "title": "Principle  of Optimality  - Dynamic Programming introduction - Abdul Bari", "start": 409.24, "end": 417.68, "text": " time is there any way to reduce the time let us observe see in this function F of 1"}, {"number": "4", "title": "Principle  of Optimality  - Dynamic Programming introduction - Abdul Bari", "start": 417.68, "end": 425.68, "text": " fib of 1 1 1 so many times it is being called so many times so if I take fib of 2 it is"}, {"number": "4", "title": "Principle  of Optimality  - Dynamic Programming introduction - Abdul Bari", "start": 425.68, "end": 431.04, "text": " called here and here and here why to call the same function again and again for the"}, {"number": "4", "title": "Principle  of Optimality  - Dynamic Programming introduction - Abdul Bari", "start": 431.04, "end": 438.64, "text": " same parameter why can't we reduce this one so yes with this idea we can reduce the function"}, {"number": "4", "title": "Principle  of Optimality  - Dynamic Programming introduction - Abdul Bari", "start": 438.64, "end": 445.15999999999997, "text": " calls and reduce the time taken by this Fibonacci function so what I'll do is I'll try to store"}, {"number": "4", "title": "Principle  of Optimality  - Dynamic Programming introduction - Abdul Bari", "start": 445.15999999999997, "end": 450.96, "text": " the result of Fibonacci function so that once it is called for fib of 2 it should not be"}, {"number": "4", "title": "Principle  of Optimality  - Dynamic Programming introduction - Abdul Bari", "start": 450.96, "end": 458.28, "text": " called again so let me show you how it can be done we will take one global array let"}, {"number": "4", "title": "Principle  of Optimality  - Dynamic Programming introduction - Abdul Bari", "start": 458.28, "end": 468.52, "text": " us say I have an array 0 1 2 3 4 5 I have an array initially I will fill this array"}, {"number": "4", "title": "Principle  of Optimality  - Dynamic Programming introduction - Abdul Bari", "start": 468.59999999999997, "end": 473.96, "text": " with minus 1 because nothing is known now let me trace this from tree once again not"}, {"number": "4", "title": "Principle  of Optimality  - Dynamic Programming introduction - Abdul Bari", "start": 473.96, "end": 478.2, "text": " function I have to modify the function but I will not modify it just from the tree I"}, {"number": "4", "title": "Principle  of Optimality  - Dynamic Programming introduction - Abdul Bari", "start": 478.2, "end": 486.28, "text": " will show you first function is called fib of 5 minus 1 we don't know so make the calls"}, {"number": "4", "title": "Principle  of Optimality  - Dynamic Programming introduction - Abdul Bari", "start": 486.28, "end": 491.59999999999997, "text": " so first call is this one fib of 3 minus 1 we don't know call the function so fib of"}, {"number": "4", "title": "Principle  of Optimality  - Dynamic Programming introduction - Abdul Bari", "start": 491.59999999999997, "end": 496.59999999999997, "text": " 1 do we know this no so call the function so what is the result of the function when"}, {"number": "4", "title": "Principle  of Optimality  - Dynamic Programming introduction - Abdul Bari", "start": 496.6, "end": 505.6, "text": " value is 1 it is 1 so mark it as 1 so this is completed then go back fib of 2 do we know"}, {"number": "4", "title": "Principle  of Optimality  - Dynamic Programming introduction - Abdul Bari", "start": 505.6, "end": 510.40000000000003, "text": " the answer for this one fib of 2 no call this fib of 0 do we know the answer for this one"}, {"number": "4", "title": "Principle  of Optimality  - Dynamic Programming introduction - Abdul Bari", "start": 510.40000000000003, "end": 517.6800000000001, "text": " no fib of 0 function is called so it is less than 1 so it will return 0 only so this becomes"}, {"number": "4", "title": "Principle  of Optimality  - Dynamic Programming introduction - Abdul Bari", "start": 517.6800000000001, "end": 526.52, "text": " 0 then fib of 1 till here the calling is done fib of 1 we already know fib of 1 don't call"}, {"number": "4", "title": "Principle  of Optimality  - Dynamic Programming introduction - Abdul Bari", "start": 526.52, "end": 533.56, "text": " this function then this result is how much 0 this value is how much 1 so add this and"}, {"number": "4", "title": "Principle  of Optimality  - Dynamic Programming introduction - Abdul Bari", "start": 533.56, "end": 539.56, "text": " return the result so this becomes 1 so fib of 2 also becomes 1 now this one then this"}, {"number": "4", "title": "Principle  of Optimality  - Dynamic Programming introduction - Abdul Bari", "start": 539.56, "end": 545.0799999999999, "text": " result fib of 1 is 1 1 plus 1 we know this result so add this and get the result for"}, {"number": "4", "title": "Principle  of Optimality  - Dynamic Programming introduction - Abdul Bari", "start": 545.0799999999999, "end": 552.84, "text": " this 2 fib of 3 is stored that is 2 now come to this side see 1 function was skipped fib"}, {"number": "4", "title": "Principle  of Optimality  - Dynamic Programming introduction - Abdul Bari", "start": 552.84, "end": 559.2, "text": " of 4 do we know we don't know then let us call the function fib of 2 shall we call no"}, {"number": "4", "title": "Principle  of Optimality  - Dynamic Programming introduction - Abdul Bari", "start": 559.2, "end": 563.88, "text": " we already know the result so don't call this function so all these functions will not be"}, {"number": "4", "title": "Principle  of Optimality  - Dynamic Programming introduction - Abdul Bari", "start": 563.88, "end": 570.72, "text": " called this is already 1 then fib of 3 do we know yes we know the answer don't call all"}, {"number": "4", "title": "Principle  of Optimality  - Dynamic Programming introduction - Abdul Bari", "start": 570.72, "end": 575.64, "text": " these functions don't call these function so first of all this is not called so automatically"}, {"number": "4", "title": "Principle  of Optimality  - Dynamic Programming introduction - Abdul Bari", "start": 575.64, "end": 581.88, "text": " these are also not called what is the result of this this is 2 then these 2 are added 1"}, {"number": "4", "title": "Principle  of Optimality  - Dynamic Programming introduction - Abdul Bari", "start": 581.88, "end": 588.96, "text": " plus 2 so this becomes 3 this becomes 3 now adding of these 2 is done 2 plus 3 that is"}, {"number": "4", "title": "Principle  of Optimality  - Dynamic Programming introduction - Abdul Bari", "start": 588.96, "end": 604.92, "text": " 5 5 that's all if we count the number of calls now this is 1 2 3 4 5 this is not called 6"}, {"number": "4", "title": "Principle  of Optimality  - Dynamic Programming introduction - Abdul Bari", "start": 604.92, "end": 613.4799999999999, "text": " that's all total 6 calls so when I have given fib of n so it is making how many calls n plus 1"}, {"number": "4", "title": "Principle  of Optimality  - Dynamic Programming introduction - Abdul Bari", "start": 613.4799999999999, "end": 622.4399999999999, "text": " calls so n plus 1 calls is what order of n theta of n or big O of n whatever you say notations so"}, {"number": "4", "title": "Principle  of Optimality  - Dynamic Programming introduction - Abdul Bari", "start": 622.4399999999999, "end": 630.92, "text": " this is order of n see this is memoization this is the result of memoization by storing the results"}, {"number": "4", "title": "Principle  of Optimality  - Dynamic Programming introduction - Abdul Bari", "start": 630.92, "end": 636.24, "text": " of the function we are avoiding the same call once again like fib of 2 already stored don't"}, {"number": "4", "title": "Principle  of Optimality  - Dynamic Programming introduction - Abdul Bari", "start": 636.24, "end": 642.4399999999999, "text": " call it again fib of 3 already found don't call it again how do you know it is already found we"}, {"number": "4", "title": "Principle  of Optimality  - Dynamic Programming introduction - Abdul Bari", "start": 642.4399999999999, "end": 648.04, "text": " can store the result in some array so this function we can modify the calls are made here"}, {"number": "4", "title": "Principle  of Optimality  - Dynamic Programming introduction - Abdul Bari", "start": 648.04, "end": 654.5999999999999, "text": " I can make them as conditional calls so based on condition the calls are made and the results are"}, {"number": "4", "title": "Principle  of Optimality  - Dynamic Programming introduction - Abdul Bari", "start": 654.5999999999999, "end": 660.7199999999999, "text": " stored in an array so the number of calls are reduced we can see that memoization has reduced"}, {"number": "4", "title": "Principle  of Optimality  - Dynamic Programming introduction - Abdul Bari", "start": 660.76, "end": 669.96, "text": " the time from 2 power n to n so from 2 power n to n so exponential to polynomial back to linear"}, {"number": "4", "title": "Principle  of Optimality  - Dynamic Programming introduction - Abdul Bari", "start": 669.96, "end": 676.48, "text": " so in this example there is a big change in other examples at least there will be some difference"}, {"number": "4", "title": "Principle  of Optimality  - Dynamic Programming introduction - Abdul Bari", "start": 676.48, "end": 683.8000000000001, "text": " memoization will bring some difference this is the approach of memoization and in this we can"}, {"number": "4", "title": "Principle  of Optimality  - Dynamic Programming introduction - Abdul Bari", "start": 683.8000000000001, "end": 689.96, "text": " see this the tree is generated and the function calls are avoided and the result is obtained back"}, {"number": "4", "title": "Principle  of Optimality  - Dynamic Programming introduction - Abdul Bari", "start": 690.1600000000001, "end": 697.6, "text": " right so from here we started so we say this is top-down approach so memoization follows"}, {"number": "4", "title": "Principle  of Optimality  - Dynamic Programming introduction - Abdul Bari", "start": 697.6, "end": 704.4000000000001, "text": " top-down approach if we want we can follow this in dynamic programming but we don't use this we"}, {"number": "4", "title": "Principle  of Optimality  - Dynamic Programming introduction - Abdul Bari", "start": 704.4000000000001, "end": 711.36, "text": " use iterative method mostly that is tabulation method the same problem how I can solve it using"}, {"number": "4", "title": "Principle  of Optimality  - Dynamic Programming introduction - Abdul Bari", "start": 711.36, "end": 717.2800000000001, "text": " tabulation method I'll show you now here is a iterative function that is using loop same"}, {"number": "4", "title": "Principle  of Optimality  - Dynamic Programming introduction - Abdul Bari", "start": 717.4, "end": 723.76, "text": " function for finding Fibonacci series or nth term of Fibonacci series see the formula f of n minus"}, {"number": "4", "title": "Principle  of Optimality  - Dynamic Programming introduction - Abdul Bari", "start": 723.76, "end": 730.48, "text": " 2 and n minus 1 the same formula is used but this is using loop let us see how this function works"}, {"number": "4", "title": "Principle  of Optimality  - Dynamic Programming introduction - Abdul Bari", "start": 730.48, "end": 737.52, "text": " if I have to find out fib of 5 that is fifth term I want to find out so it will enter inside here if"}, {"number": "4", "title": "Principle  of Optimality  - Dynamic Programming introduction - Abdul Bari", "start": 737.52, "end": 742.28, "text": " n is less than equal to 1 it will return that same thing once if it is 0 or 1 directly I'm returning"}, {"number": "4", "title": "Principle  of Optimality  - Dynamic Programming introduction - Abdul Bari", "start": 742.28, "end": 753.0, "text": " otherwise it will fill f of 0 as 0 this is 0 as 0 f of 1 as 1 this is 1 then the loop starts from"}, {"number": "4", "title": "Principle  of Optimality  - Dynamic Programming introduction - Abdul Bari", "start": 753.0, "end": 761.76, "text": " i value as 2 onward so I will start from 2 onwards so 2 to n n is what 5 in our example so 2 to n it"}, {"number": "4", "title": "Principle  of Optimality  - Dynamic Programming introduction - Abdul Bari", "start": 761.76, "end": 768.8, "text": " will go and every time for getting any ith term it will add previous two terms so for getting this"}, {"number": "4", "title": "Principle  of Optimality  - Dynamic Programming introduction - Abdul Bari", "start": 768.92, "end": 774.56, "text": " term it will add these two terms so this is i minus 2 and this is i minus 1 added so this is 1"}, {"number": "4", "title": "Principle  of Optimality  - Dynamic Programming introduction - Abdul Bari", "start": 774.56, "end": 786.16, "text": " next is i plus plus so i moves to next and add these two then i plus plus add these two then"}, {"number": "4", "title": "Principle  of Optimality  - Dynamic Programming introduction - Abdul Bari", "start": 786.16, "end": 793.8399999999999, "text": " add these two so it returns f of n n is what 5 so f of 5 that is answer is 5 fifth term is 5 only"}, {"number": "4", "title": "Principle  of Optimality  - Dynamic Programming introduction - Abdul Bari", "start": 793.84, "end": 803.12, "text": " here this is how a table is generated by this function so this is how we write the algorithms"}, {"number": "4", "title": "Principle  of Optimality  - Dynamic Programming introduction - Abdul Bari", "start": 803.12, "end": 809.52, "text": " for dynamic programming we write mostly iterative functions only which will fill up the table to get"}, {"number": "4", "title": "Principle  of Optimality  - Dynamic Programming introduction - Abdul Bari", "start": 809.52, "end": 814.8000000000001, "text": " the values and the filling is done from which on which value onward sees from smaller value onwards"}, {"number": "4", "title": "Principle  of Optimality  - Dynamic Programming introduction - Abdul Bari", "start": 814.8000000000001, "end": 821.4000000000001, "text": " so we say this is bottom-up approach we wanted 5 so we started from 0 onwards and we reach 5"}, {"number": "4", "title": "Principle  of Optimality  - Dynamic Programming introduction - Abdul Bari", "start": 821.52, "end": 828.36, "text": " whereas in recursion if you recall this was starting from 5 then it was calling fib of 3"}, {"number": "4", "title": "Principle  of Optimality  - Dynamic Programming introduction - Abdul Bari", "start": 828.36, "end": 834.8, "text": " and fib of 4 so from top it was starting then it was going till bottom then it was coming back"}, {"number": "4", "title": "Principle  of Optimality  - Dynamic Programming introduction - Abdul Bari", "start": 834.8, "end": 841.6, "text": " again so it was a top-down but this is from 0 it has started first so this is bottom-up approach"}, {"number": "4", "title": "Principle  of Optimality  - Dynamic Programming introduction - Abdul Bari", "start": 841.6, "end": 846.88, "text": " so the approach are different mostly tabulation is used if you want to frame it as recursion"}, {"number": "4", "title": "Principle  of Optimality  - Dynamic Programming introduction - Abdul Bari", "start": 847.2, "end": 853.6, "text": " you can frame them as recursion also that's all this is the difference between tabulation method"}, {"number": "4", "title": "Principle  of Optimality  - Dynamic Programming introduction - Abdul Bari", "start": 853.6, "end": 858.72, "text": " and previously i have already shown you memoization so any of these methods can be used"}, {"number": "4", "title": "Principle  of Optimality  - Dynamic Programming introduction - Abdul Bari", "start": 858.72, "end": 862.72, "text": " but mostly the problems are solved using tabulation method in dynamic programming"}, {"number": "4", "title": "Principle  of Optimality  - Dynamic Programming introduction - Abdul Bari", "start": 863.68, "end": 867.84, "text": " the main important thing in dynamic programming is that we should get the approach for solving"}, {"number": "4", "title": "Principle  of Optimality  - Dynamic Programming introduction - Abdul Bari", "start": 867.84, "end": 874.32, "text": " the problem so if you get the idea how the strategy is working then you can solve any"}, {"number": "4", "title": "Principle  of Optimality  - Dynamic Programming introduction - Abdul Bari", "start": 874.32, "end": 879.12, "text": " other problem which is suitable for dynamic programming you can devise your own approach"}, {"number": "4", "title": "Principle  of Optimality  - Dynamic Programming introduction - Abdul Bari", "start": 881.36, "end": 885.2800000000001, "text": " right so i will be focusing on that one how to get the idea"}, {"number": "4", "title": "Principle  of Optimality  - Dynamic Programming introduction - Abdul Bari", "start": 885.2800000000001, "end": 891.2800000000001, "text": " of solving a problem so watch next video on problems of dynamic programming"}], "text": " Hi the topic is dynamic programming in this video I'll give you introduction to dynamic programming give you differences between dynamic programming and greedy method and also I will show the difference between memoization and tabular method by taking an example in detail. Let us know the difference between greedy method and dynamic programming which is very very important. Greedy method and dynamic programming both are used for solving optimization problems both are different strategies but the purpose is same. Optimization problems are those which requires either minimum result or maximum result. The methods are different in greedy method we try to follow predefined procedure to get the optimal result. The procedure is known to be optimal we follow the procedure to get best result like Kruskal's method for finding minimum cost spanning tree always select a minimum cost edge and that gives us best result or Dijkstra shortest path algorithm always select the shortest path vertex and continue relaxing the vertices so you get the shortest path. So there is a predefined procedure but in dynamic programming we will try to find out all possible solutions and then pick up the best solution the optimal solution. This approach is different and it is little time consuming compared to greedy method. For any problem there may be many solutions which are feasible so we will try out all those solutions and then pick up the best one and mostly dynamic programming problems are solved by using recursive formulas though we will not use recursion of programming but the formulas are recursive if we want we can use recursion also but mostly they are solved using iteration and dynamic programming follows principle of optimality. Principle of optimality says that a problem can be solved by taking sequence of decisions to get the optimal solution. So now I can highlight one difference here in greedy method decision is taken one time that we will do it like this and we follow that procedure. In dynamic programming every stage we take a decision so this point you can understand only while solving the problem so while solving the problem I will show you perfectly how dynamic programming is working there to solve a problem. Let us see how dynamic programming adopts tabulation method or memoization difference between tabulation and memoization. I have an example function here this is the recursive definition of a Fibonacci term and this is a function or an algorithm for finding Fibonacci term and it is a recursive function the definition itself is recursive so the function is recursive. So what is Fibonacci series it starts from 0 and 1 1 every term is obtained by adding previous two terms so 2 plus 1 that is 3 and 2 plus 3 that is 5 and 5 plus 3 that is 8 and this is 13 and so on so this is 0th term first term second third fourth fifth sixth seventh and goes on. Suppose I want to know 10th term of Fibonacci series then call this function this function will give us 10th term. Now I will show you how this function works if I want to find out any term because the function is recursive so let us trace this function when I call this function for Fibonacci of 5th term I want to find out if I trace this n is less than equal to 1 no it is not less than equal to 1 if so then it will return n only otherwise it will call two functions add their results and return the result so what are those two functions it is calling it is calling itself for Fibonacci of 3 and Fibonacci of 4. So first of all it will call this one right then that one so if we see this again it will enter inside and then it's not less than equal to 1 so it will call itself for 2 times for 3 minus 2 that is Fib of 1 and then Fib of 2 then out of this it will pick up this call first so Fib of 1 directly we get the answer 1 so this is 1 then it will come this side so there are two calls here this is Fib of 0 and Fib of 1 for Fib of 0 and Fib of 1 there is no recursive call direct result is return so here the functions terminates then it will add these two terms and give the result it will add these two terms and give the result then this side it has to continue so on this side again for Fibonacci of 4 it will call itself for Fibonacci of 2 and this side for Fibonacci of 3 but first of all this is done so this is Fib of 0 and Fib of 1 this side Fib of 1 and Fib of 2 again this is Fib of 0 and Fib of 1 this will be the tracing tree of that particular function so for finding Fib of 5 it is making total 15 calls now if I consider all the calls and find out the time complexity of this one so from the function if I see this is n minus 2 and that is n minus 1 if I assume roughly it is n minus 1 only then I can prepare a recurrence relation for this one what it will be tn is equals to it is calling itself for two time let us assume n minus 1 only so 2 tn minus 1 though this is n minus 2 but if we take n minus 2 we cannot come to the conclusion so I am taking it as 1 right approximately so this is 2 tn minus 1 and what it is doing every time just adding so this is the recurrence relation and by master's theorem for decreasing function if you take this is big O of 2 power n like this is not exact it is n minus 2 it is less I have taken n minus 1 only so this upper bound for that function so the time taken by this function is big O of 2 power n right recurrence relation how to prepare there is a video available you can watch that one so how to prepare a recurrence relation so this recurrence relation is big O of 2 power n means if I call this Fibonacci function it will take so much time 2 power n exponential time is there any way to reduce the time let us observe see in this function F of 1 fib of 1 1 1 so many times it is being called so many times so if I take fib of 2 it is called here and here and here why to call the same function again and again for the same parameter why can't we reduce this one so yes with this idea we can reduce the function calls and reduce the time taken by this Fibonacci function so what I'll do is I'll try to store the result of Fibonacci function so that once it is called for fib of 2 it should not be called again so let me show you how it can be done we will take one global array let us say I have an array 0 1 2 3 4 5 I have an array initially I will fill this array with minus 1 because nothing is known now let me trace this from tree once again not function I have to modify the function but I will not modify it just from the tree I will show you first function is called fib of 5 minus 1 we don't know so make the calls so first call is this one fib of 3 minus 1 we don't know call the function so fib of 1 do we know this no so call the function so what is the result of the function when value is 1 it is 1 so mark it as 1 so this is completed then go back fib of 2 do we know the answer for this one fib of 2 no call this fib of 0 do we know the answer for this one no fib of 0 function is called so it is less than 1 so it will return 0 only so this becomes 0 then fib of 1 till here the calling is done fib of 1 we already know fib of 1 don't call this function then this result is how much 0 this value is how much 1 so add this and return the result so this becomes 1 so fib of 2 also becomes 1 now this one then this result fib of 1 is 1 1 plus 1 we know this result so add this and get the result for this 2 fib of 3 is stored that is 2 now come to this side see 1 function was skipped fib of 4 do we know we don't know then let us call the function fib of 2 shall we call no we already know the result so don't call this function so all these functions will not be called this is already 1 then fib of 3 do we know yes we know the answer don't call all these functions don't call these function so first of all this is not called so automatically these are also not called what is the result of this this is 2 then these 2 are added 1 plus 2 so this becomes 3 this becomes 3 now adding of these 2 is done 2 plus 3 that is 5 5 that's all if we count the number of calls now this is 1 2 3 4 5 this is not called 6 that's all total 6 calls so when I have given fib of n so it is making how many calls n plus 1 calls so n plus 1 calls is what order of n theta of n or big O of n whatever you say notations so this is order of n see this is memoization this is the result of memoization by storing the results of the function we are avoiding the same call once again like fib of 2 already stored don't call it again fib of 3 already found don't call it again how do you know it is already found we can store the result in some array so this function we can modify the calls are made here I can make them as conditional calls so based on condition the calls are made and the results are stored in an array so the number of calls are reduced we can see that memoization has reduced the time from 2 power n to n so from 2 power n to n so exponential to polynomial back to linear so in this example there is a big change in other examples at least there will be some difference memoization will bring some difference this is the approach of memoization and in this we can see this the tree is generated and the function calls are avoided and the result is obtained back right so from here we started so we say this is top-down approach so memoization follows top-down approach if we want we can follow this in dynamic programming but we don't use this we use iterative method mostly that is tabulation method the same problem how I can solve it using tabulation method I'll show you now here is a iterative function that is using loop same function for finding Fibonacci series or nth term of Fibonacci series see the formula f of n minus 2 and n minus 1 the same formula is used but this is using loop let us see how this function works if I have to find out fib of 5 that is fifth term I want to find out so it will enter inside here if n is less than equal to 1 it will return that same thing once if it is 0 or 1 directly I'm returning otherwise it will fill f of 0 as 0 this is 0 as 0 f of 1 as 1 this is 1 then the loop starts from i value as 2 onward so I will start from 2 onwards so 2 to n n is what 5 in our example so 2 to n it will go and every time for getting any ith term it will add previous two terms so for getting this term it will add these two terms so this is i minus 2 and this is i minus 1 added so this is 1 next is i plus plus so i moves to next and add these two then i plus plus add these two then add these two so it returns f of n n is what 5 so f of 5 that is answer is 5 fifth term is 5 only here this is how a table is generated by this function so this is how we write the algorithms for dynamic programming we write mostly iterative functions only which will fill up the table to get the values and the filling is done from which on which value onward sees from smaller value onwards so we say this is bottom-up approach we wanted 5 so we started from 0 onwards and we reach 5 whereas in recursion if you recall this was starting from 5 then it was calling fib of 3 and fib of 4 so from top it was starting then it was going till bottom then it was coming back again so it was a top-down but this is from 0 it has started first so this is bottom-up approach so the approach are different mostly tabulation is used if you want to frame it as recursion you can frame them as recursion also that's all this is the difference between tabulation method and previously i have already shown you memoization so any of these methods can be used but mostly the problems are solved using tabulation method in dynamic programming the main important thing in dynamic programming is that we should get the approach for solving the problem so if you get the idea how the strategy is working then you can solve any other problem which is suitable for dynamic programming you can devise your own approach right so i will be focusing on that one how to get the idea of solving a problem so watch next video on problems of dynamic programming"}